auto_translate/__init__.py
auto_translate/auto_translate.py
auto_translate-1.5.dist-info/METADATA
auto_translate-1.5.dist-info/WHEEL
auto_translate-1.5.dist-info/top_level.txt
auto_translate-1.5.dist-info/RECORD
