Metadata-Version: 2.1
Name: auto_translate
Version: 1.5
Summary: A simple automatic translation library
Home-page: 
Author: v4d6
Author-email: 
Classifier: Programming Language :: Python :: 3
Classifier: License :: OSI Approved :: MIT License
Classifier: Operating System :: OS Independent
Requires-Python: >=3.6
Requires-Dist: deep_translator
Requires-Dist: langdetect
